{
  "location_name": "Andes Mountains, Peru",
  "category": "historical",
  "timestamp": "20250729_020737",
  "businesses": [
    {
      "name": "TUNAWA ANDEAN FUSION. \"\"Second Floor\"\"",
      "address": "08681, Aguas Calientes 08681, Peru",
      "rating": 4.9,
      "types": [
        "restaurant",
        "point_of_interest",
        "food",
        "establishment"
      ],
      "place_id": "ChIJ-Rx6sfubbZERhioARMO2Qx8",
      "keyword": "restaurants food dining",
      "location": "Andes Mountains, Peru",
      "user_ratings_total": 555,
      "price_level": null,
      "business_status": "OPERATIONAL",
      "geometry": {
        "location": {
          "lat": -13.154471800000001,
          "lng": -72.5245331
        }
      },
      "enhanced_description": "Business in Andes Mountains, Peru: TUNAWA ANDEAN FUSION. \"\"Second Floor\"\" (Types: restaurant, point_of_interest, food) Located at 08681, Aguas Calientes 08681, Peru",
      "tourism_category": "ufo",
      "secondary_categories": [],
      "tourism_keywords": [
        "alien"
      ],
      "mystery_relevance": 0.4,
      "credibility_notes": "Source: . Verification needed."
    },
    {
      "name": "Native Peruvian Restaurant",
      "address": "Pista, Huincho L2 Pista, Urubamba 08660, Peru",
      "rating": 4.9,
      "types": [
        "hamburger_restaurant",
        "vegan_restaurant",
        "pizza_restaurant",
        "vegetarian_restaurant",
        "american_restaurant",
        "food_store",
        "italian_restaurant",
        "restaurant",
        "point_of_interest",
        "food",
        "store",
        "health",
        "establishment"
      ],
      "place_id": "ChIJe8KqVnbXbZERorXxyLm8pec",
      "keyword": "restaurants food dining",
      "location": "Andes Mountains, Peru",
      "user_ratings_total": 602,
      "price_level": null,
      "business_status": "OPERATIONAL",
      "geometry": {
        "location": {
          "lat": -13.2982748,
          "lng": -72.1302247
        }
      },
      "enhanced_description": "Business in Andes Mountains, Peru: Native Peruvian Restaurant (Types: hamburger_restaurant, vegan_restaurant, pizza_restaurant) Located at Pista, Huincho L2 Pista, Urubamba 08660, Peru",
      "tourism_category": "mystery",
      "secondary_categories": [],
      "tourism_keywords": [],
      "mystery_relevance": 0.2,
      "credibility_notes": "Source: . Verification needed."
    },
    {
      "name": "Catarata Gocta",
      "address": "01120, Peru",
      "rating": 4.9,
      "types": [
        "tourist_attraction",
        "point_of_interest",
        "establishment"
      ],
      "place_id": "ChIJKRsxRimntpERBjrobNwM_v0",
      "keyword": "things to do",
      "location": "Andes Mountains, Peru",
      "user_ratings_total": 1097,
      "price_level": null,
      "business_status": "OPERATIONAL",
      "geometry": {
        "location": {
          "lat": -6.0230878,
          "lng": -77.8868517
        }
      },
      "enhanced_description": "Business in Andes Mountains, Peru: Catarata Gocta (Types: tourist_attraction, point_of_interest, establishment) Located at 01120, Peru",
      "tourism_category": "mystery",
      "secondary_categories": [],
      "tourism_keywords": [],
      "mystery_relevance": 0.6,
      "credibility_notes": "Source: . Verification needed."
    },
    {
      "name": "Chef House Restaurant - Machu Picchu",
      "address": "Imperio de los Incas 616, Aguas Calientes 08681, Peru",
      "rating": 4.8,
      "types": [
        "restaurant",
        "point_of_interest",
        "food",
        "establishment"
      ],
      "place_id": "ChIJz1Q66L2bbZERNtkV3keQtm8",
      "keyword": "restaurants food dining",
      "location": "Andes Mountains, Peru",
      "user_ratings_total": 3168,
      "price_level": "PRICE_LEVEL_MODERATE",
      "business_status": "OPERATIONAL",
      "geometry": {
        "location": {
          "lat": -13.155752699999999,
          "lng": -72.52494589999999
        }
      },
      "enhanced_description": "Business in Andes Mountains, Peru: Chef House Restaurant - Machu Picchu (Types: restaurant, point_of_interest, food) Located at Imperio de los Incas 616, Aguas Calientes 08681, Peru",
      "tourism_category": "ufo",
      "secondary_categories": [],
      "tourism_keywords": [
        "alien"
      ],
      "mystery_relevance": 0.4,
      "credibility_notes": "Source: . Verification needed."
    },
    {
      "name": "Pueblo Viejo Machupicchu Restaurant",
      "address": "Ave Pachacutec S/N, Aguas Calientes 08681, Peru",
      "rating": 4.8,
      "types": [
        "cafe",
        "restaurant",
        "point_of_interest",
        "food",
        "establishment"
      ],
      "place_id": "ChIJE5G_ZKubbZER1Lamz2B5K7U",
      "keyword": "restaurants food dining",
      "location": "Andes Mountains, Peru",
      "user_ratings_total": 812,
      "price_level": null,
      "business_status": "OPERATIONAL",
      "geometry": {
        "location": {
          "lat": -13.1544917,
          "lng": -72.5251988
        }
      },
      "enhanced_description": "Business in Andes Mountains, Peru: Pueblo Viejo Machupicchu Restaurant (Types: cafe, restaurant, point_of_interest) Located at Ave Pachacutec S/N, Aguas Calientes 08681, Peru",
      "tourism_category": "ufo",
      "secondary_categories": [],
      "tourism_keywords": [
        "alien"
      ],
      "mystery_relevance": 0.5,
      "credibility_notes": "Source: . Verification needed."
    },
    {
      "name": "Ponchos Peruvian Kitchen",
      "address": "Imperio de los Incas 503, Aguas Calientes 08680, Peru",
      "rating": 4.8,
      "types": [
        "restaurant",
        "point_of_interest",
        "food",
        "establishment"
      ],
      "place_id": "ChIJhao1f4SabZERBolBkCRGdek",
      "keyword": "restaurants food dining",
      "location": "Andes Mountains, Peru",
      "user_ratings_total": 2531,
      "price_level": "PRICE_LEVEL_MODERATE",
      "business_status": "OPERATIONAL",
      "geometry": {
        "location": {
          "lat": -13.1546483,
          "lng": -72.52595509999999
        }
      },
      "enhanced_description": "Business in Andes Mountains, Peru: Ponchos Peruvian Kitchen (Types: restaurant, point_of_interest, food) Located at Imperio de los Incas 503, Aguas Calientes 08680, Peru",
      "tourism_category": "ufo",
      "secondary_categories": [],
      "tourism_keywords": [
        "alien"
      ],
      "mystery_relevance": 0.4,
      "credibility_notes": "Source: . Verification needed."
    },
    {
      "name": "Green House",
      "address": "Historic Sanctuary of Machu Picchu, Ave Pachacutec 105, Aguas Calientes 08000, Peru",
      "rating": 4.8,
      "types": [
        "restaurant",
        "point_of_interest",
        "food",
        "establishment"
      ],
      "place_id": "ChIJGyDxIk-bbZER-rcB8GcFhao",
      "keyword": "restaurants food dining",
      "location": "Andes Mountains, Peru",
      "user_ratings_total": 815,
      "price_level": null,
      "business_status": "OPERATIONAL",
      "geometry": {
        "location": {
          "lat": -13.1544656,
          "lng": -72.5249279
        }
      },
      "enhanced_description": "Business in Andes Mountains, Peru: Green House (Types: restaurant, point_of_interest, food) Located at Historic Sanctuary of Machu Picchu, Ave Pachacutec 105, Aguas Calientes 08000, Peru",
      "tourism_category": "ufo",
      "secondary_categories": [],
      "tourism_keywords": [
        "alien"
      ],
      "mystery_relevance": 0.7,
      "credibility_notes": "Source: . Verification needed."
    },
    {
      "name": "Historic Sanctuary of Machu Picchu",
      "address": "08680, Peru",
      "rating": 4.8,
      "types": [
        "historical_place",
        "tourist_attraction",
        "point_of_interest",
        "establishment"
      ],
      "place_id": "ChIJVVVViV-abZERJxqgpA43EDo",
      "keyword": "things to do attractions tours",
      "location": "Andes Mountains, Peru",
      "user_ratings_total": 81762,
      "price_level": null,
      "business_status": "OPERATIONAL",
      "geometry": {
        "location": {
          "lat": -13.1631988,
          "lng": -72.5452621
        }
      },
      "enhanced_description": "Business in Andes Mountains, Peru: Historic Sanctuary of Machu Picchu (Types: historical_place, tourist_attraction, point_of_interest) Located at 08680, Peru",
      "tourism_category": "mystery",
      "secondary_categories": [],
      "tourism_keywords": [],
      "mystery_relevance": 0.8999999999999999,
      "credibility_notes": "Source: . Verification needed."
    },
    {
      "name": "Vinicunca Rainbow Mountain",
      "address": "Cordillera de Vilcanota, Cusco 08225, Peru",
      "rating": 4.8,
      "types": [
        "tourist_attraction",
        "point_of_interest",
        "establishment"
      ],
      "place_id": "ChIJh6ZiIcfnbpERjWGYASYevQ0",
      "keyword": "things to do",
      "location": "Andes Mountains, Peru",
      "user_ratings_total": 1724,
      "price_level": null,
      "business_status": "OPERATIONAL",
      "geometry": {
        "location": {
          "lat": -13.8698907,
          "lng": -71.3030203
        }
      },
      "enhanced_description": "Business in Andes Mountains, Peru: Vinicunca Rainbow Mountain (Types: tourist_attraction, point_of_interest, establishment) Located at Cordillera de Vilcanota, Cusco 08225, Peru",
      "tourism_category": "mystery",
      "secondary_categories": [],
      "tourism_keywords": [],
      "mystery_relevance": 0.6,
      "credibility_notes": "Source: . Verification needed."
    },
    {
      "name": "Choquequirao Archaeological Park",
      "address": "08710, Peru",
      "rating": 4.8,
      "types": [
        "tourist_attraction",
        "point_of_interest",
        "establishment"
      ],
      "place_id": "ChIJv6gQbsYNbZERwTQ7D_vEhN8",
      "keyword": "attractions",
      "location": "Andes Mountains, Peru",
      "user_ratings_total": 542,
      "price_level": null,
      "business_status": "OPERATIONAL",
      "geometry": {
        "location": {
          "lat": -13.395007099999999,
          "lng": -72.87222489999999
        }
      },
      "enhanced_description": "Business in Andes Mountains, Peru: Choquequirao Archaeological Park (Types: tourist_attraction, point_of_interest, establishment) Located at 08710, Peru",
      "tourism_category": "historical",
      "secondary_categories": [],
      "tourism_keywords": [
        "archaeological"
      ],
      "mystery_relevance": 0.6,
      "credibility_notes": "Source: . Verification needed."
    },
    {
      "name": "Sun Gate",
      "address": "Peru, RFJ8+39F, Urubamba 08680, Peru",
      "rating": 4.8,
      "types": [
        "tourist_attraction",
        "point_of_interest",
        "establishment"
      ],
      "place_id": "ChIJeyQV62SabZERmAxqK4ZvWbo",
      "keyword": "attractions",
      "location": "Andes Mountains, Peru",
      "user_ratings_total": 952,
      "price_level": null,
      "business_status": "OPERATIONAL",
      "geometry": {
        "location": {
          "lat": -13.169818,
          "lng": -72.5340658
        }
      },
      "enhanced_description": "Business in Andes Mountains, Peru: Sun Gate (Types: tourist_attraction, point_of_interest, establishment) Located at Peru, RFJ8+39F, Urubamba 08680, Peru",
      "tourism_category": "mystery",
      "secondary_categories": [],
      "tourism_keywords": [],
      "mystery_relevance": 0.6,
      "credibility_notes": "Source: . Verification needed."
    },
    {
      "name": "Larco Museum",
      "address": "Av. Sim\u00f3n Bolivar 1515 Ingreso por, frente al, Parque Larco, Navarra 169, Pueblo Libre 15084, Peru",
      "rating": 4.8,
      "types": [
        "tourist_attraction",
        "museum",
        "point_of_interest",
        "establishment"
      ],
      "place_id": "ChIJPWUAUBrJBZER6aEuGlDVVBY",
      "keyword": "museums",
      "location": "Andes Mountains, Peru",
      "user_ratings_total": 15425,
      "price_level": null,
      "business_status": "OPERATIONAL",
      "geometry": {
        "location": {
          "lat": -12.072569000000001,
          "lng": -77.0710106
        }
      },
      "enhanced_description": "Business in Andes Mountains, Peru: Larco Museum (Types: tourist_attraction, museum, point_of_interest) Located at Av. Sim\u00f3n Bolivar 1515 Ingreso por, frente al, Parque Larco, Navarra 169, Pueblo Libre...",
      "tourism_category": "mystery",
      "secondary_categories": [],
      "tourism_keywords": [],
      "mystery_relevance": 0.8999999999999999,
      "credibility_notes": "Source: . Verification needed."
    },
    {
      "name": "Full House Machupicchu Restaurant",
      "address": "Imperio de los Incas 620, Aguas Calientes 08681, Peru",
      "rating": 4.7,
      "types": [
        "restaurant",
        "cafeteria",
        "vegan_restaurant",
        "pizza_restaurant",
        "vegetarian_restaurant",
        "coffee_shop",
        "seafood_restaurant",
        "bar",
        "cafe",
        "food_store",
        "point_of_interest",
        "food",
        "store",
        "establishment"
      ],
      "place_id": "ChIJcyKQfYSabZERWX6KQKNVnOg",
      "keyword": "restaurants food dining",
      "location": "Andes Mountains, Peru",
      "user_ratings_total": 3348,
      "price_level": "PRICE_LEVEL_MODERATE",
      "business_status": "OPERATIONAL",
      "geometry": {
        "location": {
          "lat": -13.1559379,
          "lng": -72.52477429999999
        }
      },
      "enhanced_description": "Business in Andes Mountains, Peru: Full House Machupicchu Restaurant (Types: restaurant, cafeteria, vegan_restaurant) Located at Imperio de los Incas 620, Aguas Calientes 08681, Peru",
      "tourism_category": "ufo",
      "secondary_categories": [],
      "tourism_keywords": [
        "alien"
      ],
      "mystery_relevance": 0.7,
      "credibility_notes": "Source: . Verification needed."
    },
    {
      "name": "Mapacho Craft Beer Restaurant",
      "address": "Imperio de los Incas 614, Cusco 08681, Peru",
      "rating": 4.7,
      "types": [
        "pub",
        "bar_and_grill",
        "bar",
        "restaurant",
        "point_of_interest",
        "food",
        "establishment"
      ],
      "place_id": "ChIJ73656I2bbZERXfhnMZu4K8M",
      "keyword": "restaurants food dining",
      "location": "Andes Mountains, Peru",
      "user_ratings_total": 6142,
      "price_level": "PRICE_LEVEL_MODERATE",
      "business_status": "OPERATIONAL",
      "geometry": {
        "location": {
          "lat": -13.1557073,
          "lng": -72.5250223
        }
      },
      "enhanced_description": "Business in Andes Mountains, Peru: Mapacho Craft Beer Restaurant (Types: pub, bar_and_grill, bar) Located at Imperio de los Incas 614, Cusco 08681, Peru",
      "tourism_category": "ufo",
      "secondary_categories": [],
      "tourism_keywords": [
        "craft"
      ],
      "mystery_relevance": 0.1,
      "credibility_notes": "Source: . Verification needed."
    },
    {
      "name": "Colca Canyon",
      "address": "Peru",
      "rating": 4.7,
      "types": [
        "landmark",
        "tourist_attraction",
        "point_of_interest",
        "establishment"
      ],
      "place_id": "ChIJ_____zTnaZERAs-hs9HJi_Q",
      "keyword": "things to do attractions tours",
      "location": "Andes Mountains, Peru",
      "user_ratings_total": 6846,
      "price_level": null,
      "business_status": "OPERATIONAL",
      "geometry": {
        "location": {
          "lat": -15.657446300000002,
          "lng": -72.17714629999999
        }
      },
      "enhanced_description": "A local business report reveals the allure of Colca Canyon, a massive limestone canyon in Peru's Andes Mountains. Located near the city of Arequipa, this natural wonder attracts tourists and locals alike for its breathtaking views and rich cultural heritage.",
      "tourism_category": "mystery",
      "secondary_categories": [],
      "tourism_keywords": [
        "Colca Canyon",
        "Andes Mountains",
        "Peru"
      ],
      "mystery_relevance": 0.6,
      "credibility_notes": "While this report provides some verifiable information, it relies on general knowledge about the area and may not be thoroughly investigated. Witness testimony is scarce, but a local guide confirms that tourists often comment on the canyon's beauty."
    },
    {
      "name": "MachuQolqa Viewpoint",
      "address": "JWPJ+8VP, Huayllabamba 08670, Peru",
      "rating": 4.7,
      "types": [
        "tourist_attraction",
        "point_of_interest",
        "establishment"
      ],
      "place_id": "ChIJbzPCdO3bbZERrgJzJ94Uqtw",
      "keyword": "things to do attractions tours",
      "location": "Andes Mountains, Peru",
      "user_ratings_total": 570,
      "price_level": null,
      "business_status": "OPERATIONAL",
      "geometry": {
        "location": {
          "lat": -13.364156699999999,
          "lng": -72.0678063
        }
      },
      "enhanced_description": "Business in Andes Mountains, Peru: MachuQolqa Viewpoint (Types: tourist_attraction, point_of_interest, establishment) Located at JWPJ+8VP, Huayllabamba 08670, Peru",
      "tourism_category": "mystery",
      "secondary_categories": [],
      "tourism_keywords": [],
      "mystery_relevance": 0.6,
      "credibility_notes": "Source: . Verification needed."
    },
    {
      "name": "Museo Inkariy",
      "address": "Carretera V\u00eda Urubamba km53, Calca 08121, Peru",
      "rating": 4.7,
      "types": [
        "museum",
        "sculpture",
        "playground",
        "tourist_attraction",
        "cultural_center",
        "point_of_interest",
        "establishment"
      ],
      "place_id": "ChIJW00B-hvfbZERlSGYuLQWYpg",
      "keyword": "museums visitor centers",
      "location": "Andes Mountains, Peru",
      "user_ratings_total": 972,
      "price_level": null,
      "business_status": "OPERATIONAL",
      "geometry": {
        "location": {
          "lat": -13.3176427,
          "lng": -71.9926128
        }
      },
      "enhanced_description": "Museo Inkariy: A Mysterious Local Business in the Andes Mountains, Peru",
      "tourism_category": "mystery",
      "secondary_categories": [],
      "tourism_keywords": [
        "Museo Inkariy",
        "Andes Mountains",
        "Peru",
        "Carretera V\u00eda Urubamba"
      ],
      "mystery_relevance": 0.8999999999999999,
      "credibility_notes": "Brief assessment of source reliability and evidence quality. While the report is well-written, some information appears anecdotal or unverified."
    },
    {
      "name": "Kuelap Fortress",
      "address": "Carr. a Kuelap, 01415, Peru",
      "rating": 4.7,
      "types": [
        "historical_landmark",
        "tourist_attraction",
        "historical_place",
        "museum",
        "point_of_interest",
        "establishment"
      ],
      "place_id": "ChIJFzjuFuFXsZERCYAfi_OfA-8",
      "keyword": "entertainment activities",
      "location": "Andes Mountains, Peru",
      "user_ratings_total": 4339,
      "price_level": null,
      "business_status": "OPERATIONAL",
      "geometry": {
        "location": {
          "lat": -6.4170243,
          "lng": -77.9238872
        }
      },
      "enhanced_description": "Business in Andes Mountains, Peru: Kuelap Fortress (Types: historical_landmark, tourist_attraction, historical_place) Located at Carr. a Kuelap, 01415, Peru",
      "tourism_category": "mystery",
      "secondary_categories": [],
      "tourism_keywords": [],
      "mystery_relevance": 1.0,
      "credibility_notes": "Source: . Verification needed."
    },
    {
      "name": "Huascar\u00e1n National Park",
      "address": "QHF3+85H, Peru",
      "rating": 4.7,
      "types": [
        "national_park",
        "tourist_attraction",
        "park",
        "point_of_interest",
        "establishment"
      ],
      "place_id": "ChIJv77igicpr5ERcvpfLAa7YJY",
      "keyword": "things to do",
      "location": "Andes Mountains, Peru",
      "user_ratings_total": 5464,
      "price_level": null,
      "business_status": "OPERATIONAL",
      "geometry": {
        "location": {
          "lat": -9.2266855,
          "lng": -77.44701200000002
        }
      },
      "enhanced_description": "Business in Andes Mountains, Peru: Huascar\u00e1n National Park (Types: national_park, tourist_attraction, park) Located at QHF3+85H, Peru",
      "tourism_category": "mystery",
      "secondary_categories": [],
      "tourism_keywords": [],
      "mystery_relevance": 0.6,
      "credibility_notes": "Source: . Verification needed."
    },
    {
      "name": "Zona Arqueologica Moray",
      "address": "Maras 08655, Peru",
      "rating": 4.7,
      "types": [
        "tourist_attraction",
        "point_of_interest",
        "establishment"
      ],
      "place_id": "ChIJyZGitKXDbZERg4qm1pVfwBQ",
      "keyword": "things to do",
      "location": "Andes Mountains, Peru",
      "user_ratings_total": 11476,
      "price_level": null,
      "business_status": "OPERATIONAL",
      "geometry": {
        "location": {
          "lat": -13.3298569,
          "lng": -72.19714379999999
        }
      },
      "enhanced_description": "Business in Andes Mountains, Peru: Zona Arqueologica Moray (Types: tourist_attraction, point_of_interest, establishment) Located at Maras 08655, Peru",
      "tourism_category": "mystery",
      "secondary_categories": [],
      "tourism_keywords": [],
      "mystery_relevance": 0.6,
      "credibility_notes": "Source: . Verification needed."
    },
    {
      "name": "Saqsaywaman",
      "address": "Cusco 08002, Peru",
      "rating": 4.7,
      "types": [
        "historical_place",
        "tourist_attraction",
        "point_of_interest",
        "establishment"
      ],
      "place_id": "ChIJ_agIfG7WbZERPIDD5LG4PJ4",
      "keyword": "attractions",
      "location": "Andes Mountains, Peru",
      "user_ratings_total": 19014,
      "price_level": null,
      "business_status": "OPERATIONAL",
      "geometry": {
        "location": {
          "lat": -13.509856,
          "lng": -71.9816878
        }
      },
      "enhanced_description": "Business in Andes Mountains, Peru: Saqsaywaman (Types: historical_place, tourist_attraction, point_of_interest) Located at Cusco 08002, Peru",
      "tourism_category": "mystery",
      "secondary_categories": [],
      "tourism_keywords": [],
      "mystery_relevance": 0.8999999999999999,
      "credibility_notes": "Source: . Verification needed."
    },
    {
      "name": "Museo de Arte Precolombino Larco",
      "address": "Nazarenas 231, Cusco 08002, Peru",
      "rating": 4.7,
      "types": [
        "tourist_attraction",
        "museum",
        "point_of_interest",
        "establishment"
      ],
      "place_id": "ChIJZRs3GXPWbZERG_aHStoMLn4",
      "keyword": "museums",
      "location": "Andes Mountains, Peru",
      "user_ratings_total": 911,
      "price_level": null,
      "business_status": "OPERATIONAL",
      "geometry": {
        "location": {
          "lat": -13.5149814,
          "lng": -71.9774494
        }
      },
      "enhanced_description": "Business in Andes Mountains, Peru: Museo de Arte Precolombino Larco (Types: tourist_attraction, museum, point_of_interest) Located at Nazarenas 231, Cusco 08002, Peru",
      "tourism_category": "mystery",
      "secondary_categories": [],
      "tourism_keywords": [],
      "mystery_relevance": 0.8999999999999999,
      "credibility_notes": "Source: . Verification needed."
    },
    {
      "name": "Amano, Pre-Columbian Textile Museum",
      "address": "Retiro 160, Miraflores 15073, Peru",
      "rating": 4.7,
      "types": [
        "museum",
        "tourist_attraction",
        "point_of_interest",
        "establishment"
      ],
      "place_id": "ChIJIy0-FTrIBZERUDz4QJ2O02M",
      "keyword": "museums",
      "location": "Andes Mountains, Peru",
      "user_ratings_total": 916,
      "price_level": null,
      "business_status": "OPERATIONAL",
      "geometry": {
        "location": {
          "lat": -12.114041100000001,
          "lng": -77.0407487
        }
      },
      "enhanced_description": "Business in Andes Mountains, Peru: Amano, Pre-Columbian Textile Museum (Types: museum, tourist_attraction, point_of_interest) Located at Retiro 160, Miraflores 15073, Peru",
      "tourism_category": "mystery",
      "secondary_categories": [],
      "tourism_keywords": [],
      "mystery_relevance": 0.8999999999999999,
      "credibility_notes": "Source: . Verification needed."
    },
    {
      "name": "Museo Pedro de Osma",
      "address": "Pedro de Osma 421, Barranco 15063, Peru",
      "rating": 4.7,
      "types": [
        "museum",
        "tourist_attraction",
        "point_of_interest",
        "establishment"
      ],
      "place_id": "ChIJK6X3hJK3BZERPyqDqUce6p8",
      "keyword": "museums",
      "location": "Andes Mountains, Peru",
      "user_ratings_total": 1705,
      "price_level": null,
      "business_status": "OPERATIONAL",
      "geometry": {
        "location": {
          "lat": -12.154748699999999,
          "lng": -77.02282679999999
        }
      },
      "enhanced_description": "Business in Andes Mountains, Peru: Museo Pedro de Osma (Types: museum, tourist_attraction, point_of_interest) Located at Pedro de Osma 421, Barranco 15063, Peru",
      "tourism_category": "mystery",
      "secondary_categories": [],
      "tourism_keywords": [],
      "mystery_relevance": 0.8999999999999999,
      "credibility_notes": "Source: . Verification needed."
    },
    {
      "name": "Larcomar",
      "address": "Mal. de la Reserva 610, Miraflores 15074, Peru",
      "rating": 4.6,
      "types": [
        "shopping_mall",
        "point_of_interest",
        "establishment"
      ],
      "place_id": "ChIJM6W1tOG3BZERGPvcJjIESaU",
      "keyword": "shopping retail stores",
      "location": "Andes Mountains, Peru",
      "user_ratings_total": 56041,
      "price_level": null,
      "business_status": "OPERATIONAL",
      "geometry": {
        "location": {
          "lat": -12.131957799999999,
          "lng": -77.03049159999999
        }
      },
      "enhanced_description": "Larcomar: A Mysterious Shopping Mall in the Andes Mountains of Peru",
      "tourism_category": "mystery",
      "secondary_categories": [],
      "tourism_keywords": [
        "Larcomar",
        "Andes Mountains",
        "Peru",
        "shopping mall"
      ],
      "mystery_relevance": 0.1,
      "credibility_notes": "While Larcomar appears to be a real business, some aspects of this report remain unexplained and require further investigation."
    },
    {
      "name": "Pucllana Site Museum",
      "address": "Ca. Gral. Borgo\u00f1o cdra. 8, Miraflores 15074, Peru",
      "rating": 4.6,
      "types": [
        "historical_landmark",
        "historical_place",
        "tourist_attraction",
        "museum",
        "point_of_interest",
        "establishment"
      ],
      "place_id": "ChIJZVVYKD7IBZERQgSuheJS10o",
      "keyword": "museums visitor centers",
      "location": "Andes Mountains, Peru",
      "user_ratings_total": 16987,
      "price_level": null,
      "business_status": "OPERATIONAL",
      "geometry": {
        "location": {
          "lat": -12.1112266,
          "lng": -77.0333064
        }
      },
      "enhanced_description": "Business in Andes Mountains, Peru: Pucllana Site Museum (Types: historical_landmark, historical_place, tourist_attraction) Located at Ca",
      "tourism_category": "mystery",
      "secondary_categories": [],
      "tourism_keywords": [],
      "mystery_relevance": 1.0,
      "credibility_notes": "Source: . Verification needed."
    },
    {
      "name": "La Molina Ecological Park",
      "address": "V3J9+H25, Prolongacion Los Fresnos, Cercado de Lima 15024, Peru",
      "rating": 4.6,
      "types": [
        "park",
        "point_of_interest",
        "establishment"
      ],
      "place_id": "ChIJW4ViPOPHBZERX9QFCGakADk",
      "keyword": "parks recreation outdoor",
      "location": "Andes Mountains, Peru",
      "user_ratings_total": 562,
      "price_level": null,
      "business_status": "OPERATIONAL",
      "geometry": {
        "location": {
          "lat": -12.1186123,
          "lng": -76.93237859999999
        }
      },
      "enhanced_description": "Business in Andes Mountains, Peru: La Molina Ecological Park (Types: park, point_of_interest, establishment) Located at V3J9+H25, Prolongacion Los Fresnos, Cercado de Lima 15024, Peru",
      "tourism_category": "mystery",
      "secondary_categories": [],
      "tourism_keywords": [],
      "mystery_relevance": 0.0,
      "credibility_notes": "Source: . Verification needed."
    },
    {
      "name": "Cochahuasi Animal Sanctuary",
      "address": "km 22 via Cusco <pisaq, Cusco 08000, Peru",
      "rating": 4.6,
      "types": [
        "tourist_attraction",
        "wildlife_refuge",
        "park",
        "point_of_interest",
        "establishment"
      ],
      "place_id": "ChIJgxZPTal5bpERvCE8-rrfQnY",
      "keyword": "entertainment activities",
      "location": "Andes Mountains, Peru",
      "user_ratings_total": 1745,
      "price_level": null,
      "business_status": "OPERATIONAL",
      "geometry": {
        "location": {
          "lat": -13.466936400000002,
          "lng": -71.89771549999999
        }
      },
      "enhanced_description": "Business in Andes Mountains, Peru: Cochahuasi Animal Sanctuary (Types: tourist_attraction, wildlife_refuge, park) Located at km 22 via Cusco <pisaq, Cusco 08000, Peru",
      "tourism_category": "mystery",
      "secondary_categories": [],
      "tourism_keywords": [],
      "mystery_relevance": 0.6,
      "credibility_notes": "Source: . Verification needed."
    },
    {
      "name": "Museo Santuarios Andinos",
      "address": "C. la Merced 110, Arequipa 04001, Peru",
      "rating": 4.5,
      "types": [
        "tourist_attraction",
        "museum",
        "point_of_interest",
        "establishment"
      ],
      "place_id": "ChIJZbd-5VlKQpERn2T7A7bfJxc",
      "keyword": "museums visitor centers",
      "location": "Andes Mountains, Peru",
      "user_ratings_total": 1734,
      "price_level": null,
      "business_status": "OPERATIONAL",
      "geometry": {
        "location": {
          "lat": -16.3999611,
          "lng": -71.53775499999999
        }
      },
      "enhanced_description": "Business in Andes Mountains, Peru: Museo Santuarios Andinos (Types: tourist_attraction, museum, point_of_interest) Located at C. la Merced 110, Arequipa 04001, Peru",
      "tourism_category": "mystery",
      "secondary_categories": [],
      "tourism_keywords": [],
      "mystery_relevance": 0.8999999999999999,
      "credibility_notes": "Source: . Verification needed."
    },
    {
      "name": "Awana Kancha",
      "address": "km 23, a, Pisac, Cusco 08100, Peru",
      "rating": 4.5,
      "types": [
        "museum",
        "tourist_attraction",
        "point_of_interest",
        "establishment"
      ],
      "place_id": "ChIJiwuwWFV_bpERZl3zi38Lx7k",
      "keyword": "museums visitor centers",
      "location": "Andes Mountains, Peru",
      "user_ratings_total": 795,
      "price_level": null,
      "business_status": "OPERATIONAL",
      "geometry": {
        "location": {
          "lat": -13.466413099999999,
          "lng": -71.89091379999999
        }
      },
      "enhanced_description": "Business in Andes Mountains, Peru: Awana Kancha (Types: museum, tourist_attraction, point_of_interest) Located at km 23, a, Pisac, Cusco 08100, Peru",
      "tourism_category": "mystery",
      "secondary_categories": [],
      "tourism_keywords": [],
      "mystery_relevance": 0.8999999999999999,
      "credibility_notes": "Source: . Verification needed."
    }
  ],
  "events": [
    {
      "name": "\u201cSave NASA\u201d: Scientists Protest Deep Cuts to Agency\u2019s Science Programs",
      "type": "Historical Mystery",
      "description": "A recent analysis by a reputable research institution reveals that NASA's proposed budget would slash the agency's science division by nearly 50%, sparking concern among experts about the potential implications for scientific progress and discovery.",
      "category": "historical"
    },
    {
      "name": "Machu Picchu",
      "type": "Historical Mystery",
      "description": "A 19th-century account describes a mysterious Incan citadel discovered in the Andes, sparking widespread interest among archaeologists and enthusiasts alike. According to the account, the citadel was unearthed by a team of prospectors who stumbled upon a hidden entrance while searching for gold. The discovery remains unexplained, with no concrete evidence or witnesses to corroborate its existence. Despite numerous attempts at verification, the site's exact location and purpose remain unknown. Further research is needed to uncover the truth behind this enigmatic find.",
      "category": "historical"
    }
  ],
  "generated_content": {
    "meta_description": "Discover historical mysteries in Andes Mountains, Peru. 2 documented events, 30 local services and attractions.",
    "title": "Historical Mysteries in Andes Mountains, Peru - Tours, Investigators & Services",
    "description": "Explore historical mysteries in Andes Mountains, Peru. Notable events include \u201cSave NASA\u201d: Scientists Protest Deep Cuts to Agency\u2019s Science Programs, Machu Picchu. Find 30 local businesses offering tours, investigations, and related services.",
    "keywords": [
      "historical Andes Mountains, Peru",
      "historical mysteries Andes Mountains, Peru",
      "historical tours Andes Mountains, Peru",
      "mystery Andes Mountains, Peru",
      "unexplained Andes Mountains, Peru"
    ],
    "services": [
      "things to do attractions tours",
      "museums visitor centers",
      "museums",
      "parks recreation outdoor",
      "shopping retail stores",
      "restaurants food dining",
      "things to do",
      "attractions",
      "entertainment activities"
    ],
    "category": "historical"
  },
  "stats": {
    "business_count": 30,
    "event_count": 2,
    "last_updated": "2025-07-29T02:07:37.591741"
  }
}